control_repository/__init__.py
control_repository/control_repository.py
control_repository/environment.py
control_repository/exceptions.py
control_repository/modules.py
control_repository/puppet_module.py
control_repository/puppetfile.py
control_repository/puppet/__init__.py
control_repository/puppet/environment.py
control_repository/puppet/puppetfile.py
py_control_repository-1.0.0.data/scripts/type_checker.sh
py_control_repository-1.0.0.dist-info/METADATA
py_control_repository-1.0.0.dist-info/WHEEL
py_control_repository-1.0.0.dist-info/top_level.txt
py_control_repository-1.0.0.dist-info/RECORD
