Metadata-Version: 2.1
Name: py-control-repository
Version: 1.0.0
Summary: Module to manage Puppet control repository hosted on Github
Home-page: https://github.com/othalla/py-control-repository
Author: Florian Chardin
Author-email: othalla.lf@gmail.com
License: UNKNOWN
Platform: UNKNOWN
Classifier: Development Status :: 5 - Production/Stable
Classifier: Environment :: Web Environment
Classifier: Intended Audience :: Developers
Classifier: License :: OSI Approved :: GNU Library or Lesser General Public License (LGPL)
Classifier: Operating System :: OS Independent
Classifier: Programming Language :: Python
Classifier: Programming Language :: Python :: 3.6
Classifier: Topic :: Software Development
Requires-Dist: PyGithub (>=1.43)
